sktl-2.3.3.dist-info/METADATA
sktl-2.3.3.dist-info/top_level.txt
sktl-2.3.3.dist-info/RECORD
sktl-2.3.3.dist-info/WHEEL
sktl-2.3.3.dist-info/LICENSE
sktl/__init__.py
sktl/tpool/tpool.cpython-36m-i386-linux-gnu.so
sktl/tpool/__init__.py
sktl/tpool/tpool.pyi
sktl/snapmail/__init__.py
sktl/snapmail/snapmail.cpython-36m-i386-linux-gnu.so
sktl/snapmail/snapmail.pyi
sktl/send/send.pyi
sktl/send/__init__.py
sktl/send/telegram.cpython-36m-i386-linux-gnu.so
sktl/send/send.cpython-36m-i386-linux-gnu.so
sktl/send/telegram.pyi
sktl/smailpro/__init__.py
sktl/smailpro/main.pyi
sktl/smailpro/main.cpython-36m-i386-linux-gnu.so
sktl/db/cursor.pyi
sktl/db/__init__.py
sktl/db/cursor.cpython-36m-i386-linux-gnu.so
sktl/db/base.cpython-36m-i386-linux-gnu.so
sktl/db/db.cpython-36m-i386-linux-gnu.so
sktl/db/base.pyi
sktl/db/db.pyi
sktl/truecaptcha/__init__.py
sktl/truecaptcha/main.pyi
sktl/truecaptcha/main.cpython-36m-i386-linux-gnu.so
sktl/msapi/OneDrive.cpython-36m-i386-linux-gnu.so
sktl/msapi/__init__.py
sktl/msapi/auth.cpython-36m-i386-linux-gnu.so
sktl/msapi/OneDrive.pyi
sktl/msapi/auth.pyi
sktl/imap/__init__.py
sktl/imap/outlook.cpython-36m-i386-linux-gnu.so
sktl/imap/outlook.pyi
