Metadata-Version: 2.1
Name: sktl
Version: 2.3.3
Summary: sk's python kits
Author: shuke
Author-email: imshuke@gmail.com
Requires-Python: >=3.6
License-File: LICENSE
Requires-Dist: httpx
Requires-Dist: msal
